frasco_push.py
setup.py
frasco_push.egg-info/PKG-INFO
frasco_push.egg-info/SOURCES.txt
frasco_push.egg-info/dependency_links.txt
frasco_push.egg-info/not-zip-safe
frasco_push.egg-info/requires.txt
frasco_push.egg-info/top_level.txt