Metadata-Version: 1.0
Name: frasco-push
Version: 0.3.1
Summary: Socket.IO integration from Frasco
Home-page: http://github.com/frascoweb/frasco-push
Author: Maxime Bouroumeau-Fuseau
Author-email: maxime.bouroumeau@gmail.com
License: MIT
Platform: any
